ascmhl/__init__.py
ascmhl/__version__.py
ascmhl/_debug_commands.py
ascmhl/chain.py
ascmhl/chain_txt_parser.py
ascmhl/chain_xml_parser.py
ascmhl/commands.py
ascmhl/context.py
ascmhl/errors.py
ascmhl/generator.py
ascmhl/hasher.py
ascmhl/hashlist.py
ascmhl/hashlist_xml_parser.py
ascmhl/history.py
ascmhl/ignore.py
ascmhl/logger.py
ascmhl/traverse.py
ascmhl/utils.py
ascmhl/cli/__init__.py
ascmhl/cli/ascmhl.py
ascmhl/cli/ascmhl_debug.py
ascmhl/cli/ascmhl_dev.py
ascmhl/cli/update.py
ascmhl-1.2.dist-info/licenses/LICENSE.md
tests/__init__.py
tests/conftest.py
tests/test_check.py
tests/test_create.py
tests/test_dirhash.py
tests/test_flatten.py
tests/test_hasher.py
tests/test_ignore.py
tests/test_ignore_extended.py
tests/test_info.py
tests/test_mhl_parsing.py
tests/test_nested.py
tests/test_paths.py
tests/test_record.py
tests/test_renaming.py
tests/test_scenarios.py
tests/test_update.py
tests/test_utils.py
tests/test_verify.py
tests/test_verify_nested.py
tests/test_version.py
ascmhl-1.2.dist-info/METADATA
ascmhl-1.2.dist-info/WHEEL
ascmhl-1.2.dist-info/entry_points.txt
ascmhl-1.2.dist-info/top_level.txt
ascmhl-1.2.dist-info/RECORD
