Metadata-Version: 2.4
Name: ascmhl
Version: 1.2
Summary: ASC Media Hash List (ASC MHL)
Home-page: https://github.com/ascmitc/mhl
Author: The ASC MHL Working Group (Alex Sahm, Ben Hagen, Jon Waggoner, Mark Hudgins, Patrick Renner, and others.)
Author-email: opensource@pomfort.com
Classifier: Programming Language :: Python :: 3 :: Only
Classifier: License :: OSI Approved :: MIT License
Classifier: Operating System :: OS Independent
Requires-Python: >=3.11
License-File: LICENSE.md
Requires-Dist: Click~=8.1.7
Requires-Dist: lxml>=4.6.2
Requires-Dist: packaging>=20.9
Requires-Dist: pathspec>=0.8.0
Requires-Dist: requests>=2.25.1
Requires-Dist: xxhash>=2.0.0
Requires-Dist: python-dateutil>=2.8.2
Requires-Dist: importlib-metadata>=4.0.1; python_version >= "3.11"
Dynamic: author
Dynamic: author-email
Dynamic: classifier
Dynamic: description
Dynamic: description-content-type
Dynamic: home-page
Dynamic: license-file
Dynamic: requires-dist
Dynamic: requires-python
Dynamic: summary
